finance_mcp/__init__.py
finance_mcp/main.py
finance_mcp/config/__init__.py
finance_mcp/config/config_parser.py
finance_mcp/config/default.yaml
finance_mcp/config/external_mcp.yaml
finance_mcp/config/stream_agent.yaml
finance_mcp/config/ths.yaml
finance_mcp/core/__init__.py
finance_mcp/core/agent/__init__.py
finance_mcp/core/agent/conduct_research_op.py
finance_mcp/core/agent/conduct_research_prompt.yaml
finance_mcp/core/agent/dashscope_deep_research_op.py
finance_mcp/core/agent/langchain_deep_research_op.py
finance_mcp/core/agent/langchain_deep_research_prompt.yaml
finance_mcp/core/agent/react_agent_op.py
finance_mcp/core/agent/react_agent_prompt.yaml
finance_mcp/core/agent/research_complete_op.py
finance_mcp/core/agent/think_tool_op.py
finance_mcp/core/agent/think_tool_prompt.yaml
finance_mcp/core/crawl/__init__.py
finance_mcp/core/crawl/crawl4ai_op.py
finance_mcp/core/crawl/ths_url_op.py
finance_mcp/core/extract/__init__.py
finance_mcp/core/extract/extract_entities_code_op.py
finance_mcp/core/extract/extract_entities_code_prompt.yaml
finance_mcp/core/extract/extract_long_text_op.py
finance_mcp/core/extract/extract_long_text_prompt.yaml
finance_mcp/core/findata/__init__.py
finance_mcp/core/findata/history_calculate_op.py
finance_mcp/core/findata/history_calculate_prompt.yaml
finance_mcp/core/findata/tushare_client.py
finance_mcp/core/gallery/__init__.py
finance_mcp/core/gallery/execute_code_op.py
finance_mcp/core/gallery/execute_code_prompt.yaml
finance_mcp/core/gallery/execute_shell_op.py
finance_mcp/core/gallery/execute_shell_prompt.yaml
finance_mcp/core/search/__init__.py
finance_mcp/core/search/dashscope_search_op.py
finance_mcp/core/search/dashscope_search_prompt.yaml
finance_mcp/core/search/mcp_search_op.py
finance_mcp/core/search/mock_search_op.py
finance_mcp/core/search/mock_search_prompt.yaml
finance_mcp/core/search/tavily_search_op.py
finance_mcp/core/search/tavily_search_prompt.yaml
finance_mcp/core/utils/__init__.py
finance_mcp-0.1.4.dist-info/licenses/LICENSE
finance_mcp-0.1.4.dist-info/METADATA
finance_mcp-0.1.4.dist-info/WHEEL
finance_mcp-0.1.4.dist-info/entry_points.txt
finance_mcp-0.1.4.dist-info/top_level.txt
finance_mcp-0.1.4.dist-info/RECORD
