Metadata-Version: 2.4
Name: finance-mcp
Version: 0.1.4
Summary: LLM-powered MCP server for building financial deep-research agents, integrating web search, Crawl4AI scraping, and entity extraction into composable analysis flows.
Author-email: "jinli.yl" <jinli.yl@alibaba-inc.com>, "taoshuchang.tsc" <taoshuchang.tsc@alibaba-inc.com>, "congling.chr" <congling.chr@alibaba-inc.com>, Jiaji Deng <dengjiaji.djj@alibaba-inc.com>
License:                                  Apache License
Project-URL: Homepage, https://github.com/flowllm-ai/finance-mcp
Project-URL: Documentation, https://flowllm-ai.github.io/finance-mcp/
Project-URL: Repository, https://github.com/flowllm-ai/finance-mcp
Keywords: llm,agent,deep-research,financial-research,mcp,model-context-protocol,flowllm,crawl4ai,web-search,tushare
Classifier: Development Status :: 4 - Beta
Classifier: Intended Audience :: Developers
Classifier: Intended Audience :: Science/Research
Classifier: License :: OSI Approved :: Apache Software License
Classifier: Operating System :: OS Independent
Classifier: Programming Language :: Python :: 3
Classifier: Programming Language :: Python :: 3.10
Classifier: Topic :: Scientific/Engineering :: Artificial Intelligence
Classifier: Topic :: Software Development :: Libraries :: Python Modules
Classifier: Topic :: Software Development :: Libraries :: Application Frameworks
Classifier: Typing :: Typed
Requires-Python: >=3.10
License-File: LICENSE
Requires-Dist: tushare
Requires-Dist: crawl4ai>=0.7.4
Requires-Dist: flowllm>=0.2.0.7
Requires-Dist: tavily-python>=0.7.13
Provides-Extra: dev
Requires-Dist: pytest>=8.4.2; extra == "dev"
Requires-Dist: pytest_asyncio>=1.2.0; extra == "dev"
Requires-Dist: pre-commit; extra == "dev"
Requires-Dist: mkdocs-shadcn; extra == "dev"
Dynamic: license-file
